embedding_tools/__init__.py
embedding_tools/arrays/__init__.py
embedding_tools/arrays/base.py
embedding_tools/arrays/jax_backend.py
embedding_tools/arrays/mlx_backend.py
embedding_tools/arrays/numpy_backend.py
embedding_tools/arrays/torch_backend.py
embedding_tools/config/__init__.py
embedding_tools/config/versioning.py
embedding_tools/memory/__init__.py
embedding_tools/memory/embedding_store.py
embedding_tools/utils/__init__.py
embedding_tools/utils/device_detection.py
embedding_tools-0.1.2.dist-info/licenses/LICENSE
embedding_tools-0.1.2.dist-info/METADATA
embedding_tools-0.1.2.dist-info/WHEEL
embedding_tools-0.1.2.dist-info/top_level.txt
embedding_tools-0.1.2.dist-info/RECORD
