Metadata-Version: 2.4
Name: embedding_tools
Version: 0.1.2
Summary: Utilities for embedding experiments with cross-platform array support
Author-email: Nitin Borwankar <nborwankar@gmail.com>
License-Expression: MIT
Project-URL: Homepage, https://github.com/nborwankar/embedding_tools
Project-URL: Repository, https://github.com/nborwankar/embedding_tools
Project-URL: Issues, https://github.com/nborwankar/embedding_tools/issues
Keywords: embeddings,machine-learning,numpy,mlx,jax,pytorch,apple-silicon
Classifier: Development Status :: 3 - Alpha
Classifier: Intended Audience :: Science/Research
Classifier: Intended Audience :: Developers
Classifier: Programming Language :: Python :: 3
Classifier: Programming Language :: Python :: 3.8
Classifier: Programming Language :: Python :: 3.9
Classifier: Programming Language :: Python :: 3.10
Classifier: Programming Language :: Python :: 3.11
Classifier: Topic :: Scientific/Engineering :: Artificial Intelligence
Requires-Python: >=3.8
License-File: LICENSE
Requires-Dist: numpy>=1.21.0
Provides-Extra: mlx
Requires-Dist: mlx>=0.0.7; extra == "mlx"
Provides-Extra: torch
Requires-Dist: torch>=2.0.0; extra == "torch"
Provides-Extra: jax
Requires-Dist: jax>=0.4.0; extra == "jax"
Requires-Dist: jax-metal>=0.1.0; sys_platform == "darwin" and extra == "jax"
Provides-Extra: dev
Requires-Dist: pytest>=7.0.0; extra == "dev"
Requires-Dist: pytest-cov>=4.0.0; extra == "dev"
Requires-Dist: black>=22.0.0; extra == "dev"
Requires-Dist: isort>=5.10.0; extra == "dev"
Requires-Dist: flake8>=4.0.0; extra == "dev"
Provides-Extra: all
Requires-Dist: mlx>=0.0.7; extra == "all"
Requires-Dist: torch>=2.0.0; extra == "all"
Requires-Dist: jax>=0.4.0; extra == "all"
Requires-Dist: jax-metal>=0.1.0; sys_platform == "darwin" and extra == "all"
Dynamic: license-file
